README.md
setup.py
padmet_utils/__init__.py
padmet_utils.egg-info/PKG-INFO
padmet_utils.egg-info/SOURCES.txt
padmet_utils.egg-info/dependency_links.txt
padmet_utils.egg-info/top_level.txt
padmet_utils/connection/__init__.py
padmet_utils/connection/biggAPI_to_padmet.py
padmet_utils/connection/check_orthology_input.py
padmet_utils/connection/enhanced_meneco_output.py
padmet_utils/connection/extract_orthofinder.py
padmet_utils/connection/extract_rxn_with_gene_assoc.py
padmet_utils/connection/gbk_to_faa.py
padmet_utils/connection/gene_to_targets.py
padmet_utils/connection/modelSeed_to_padmet.py
padmet_utils/connection/padmet_to_asp.py
padmet_utils/connection/padmet_to_matrix.py
padmet_utils/connection/padmet_to_padmet.py
padmet_utils/connection/padmet_to_tsv.py
padmet_utils/connection/pgdb_to_padmet.py
padmet_utils/connection/sbmlGenerator.py
padmet_utils/connection/sbml_to_curation_form.py
padmet_utils/connection/sbml_to_padmet.py
padmet_utils/connection/sbml_to_sbml.py
padmet_utils/connection/wikiGenerator.py
padmet_utils/exploration/__init__.py
padmet_utils/exploration/compare_padmet.py
padmet_utils/exploration/compare_sbml.py
padmet_utils/exploration/compare_sbml_padmet.py
padmet_utils/exploration/convert_sbml_db.py
padmet_utils/exploration/dendrogram_reactions_distance.py
padmet_utils/exploration/flux_analysis.py
padmet_utils/exploration/get_pwy_from_rxn.py
padmet_utils/exploration/padmet_stats.py
padmet_utils/exploration/prot2genome.py
padmet_utils/exploration/report_network.py
padmet_utils/management/__init__.py
padmet_utils/management/manual_curation.py
padmet_utils/management/padmet_compart.py
padmet_utils/management/padmet_medium.py
padmet_utils/management/relation_curation.py