Metadata-Version: 2.1
Name: padmet-utils
Version: 0.0.9
Summary: Modules to manage, explore and connect metabolic networks using Padmet and SBML formats
Home-page: https://github.com/AuReMe/padmet-utils
Author: Dyliss Inria
Author-email: gem-aureme@inria.fr
License: UNKNOWN
Platform: UNKNOWN
Classifier: Programming Language :: Python :: 3
Classifier: License :: OSI Approved :: MIT License
Classifier: Operating System :: OS Independent
